LICENSE
snowday/__init__.py
snowday/acl/__init__.py
snowday/acl/grants/__init__.py
snowday/acl/grants/account.py
snowday/acl/grants/base.py
snowday/acl/grants/common.py
snowday/acl/grants/future.py
snowday/acl/grants/role.py
snowday/acl/grants/schema.py
snowday/acl/grants/schema_object.py
snowday/acl/grants/share.py
snowday/acl/grants/util.py
snowday/connector/__init__.py
snowday/connector/core.py
snowday/context/__init__.py
snowday/context/session.py
snowday/exceptions.py
snowday/graph/__init__.py
snowday/graph/util.py
snowday/logger.py
snowday/objects/__init__.py
snowday/objects/account.py
snowday/objects/base.py
snowday/objects/base_schema.py
snowday/objects/database.py
snowday/objects/helper.py
snowday/objects/instance.py
snowday/objects/schema.py
snowday/objects/table.py
snowday/types/__init__.py
snowday/types/base.py
snowday/types/compression/__init__.py
snowday/types/compression/auto.py
snowday/types/compression/base.py
snowday/types/compression/brotli.py
snowday/types/compression/bz2.py
snowday/types/compression/deflate.py
snowday/types/compression/gzip.py
snowday/types/compression/raw_deflate.py
snowday/types/compression/snappy.py
snowday/types/compression/zstd.py
snowday/types/data/__init__.py
snowday/types/data/datetime.py
snowday/types/data/geography.py
snowday/types/data/logical.py
snowday/types/data/numeric.py
snowday/types/data/semistruct.py
snowday/types/data/string.py
snowday/types/encoding/__init__.py
snowday/types/encoding/base.py
snowday/types/encoding/big5.py
snowday/types/encoding/euc_jp.py
snowday/types/encoding/euc_kr.py
snowday/types/encoding/gb18030.py
snowday/types/encoding/ibm420.py
snowday/types/encoding/ibm424.py
snowday/types/encoding/iso_2022_cn.py
snowday/types/encoding/iso_2022_jp.py
snowday/types/encoding/iso_2022_kr.py
snowday/types/encoding/iso_8859_1.py
snowday/types/encoding/iso_8859_2.py
snowday/types/encoding/iso_8859_5.py
snowday/types/encoding/iso_8859_6.py
snowday/types/encoding/iso_8859_7.py
snowday-0.1.5.dist-info/LICENSE
snowday-0.1.5.dist-info/WHEEL
snowday-0.1.5.dist-info/METADATA
snowday-0.1.5.dist-info/RECORD
